download_databases.py
run_antismash.py
antismash/__init__.py
antismash/utils.py
antismash/config/__init__.py
antismash/config/default.cfg
antismash/db/__init__.py
antismash/db/biosql/__init__.py
antismash/db/biosql/test/AAA26493.embl
antismash/db/biosql/test/__init__.py
antismash/db/biosql/test/test_db.py
antismash/db/extradata/__init__.py
antismash/generic_genome_modules/__init__.py
antismash/generic_genome_modules/metabolicmodel/__init__.py
antismash/generic_genome_modules/metabolicmodel/augPhase.py
antismash/generic_genome_modules/metabolicmodel/automodel.py
antismash/generic_genome_modules/metabolicmodel/prunPhase.py
antismash/generic_genome_modules/metabolicmodel/input1/bigg_mnxm_compound_dict.p
antismash/generic_genome_modules/metabolicmodel/input1/bigg_mnxr_dict.p
antismash/generic_genome_modules/metabolicmodel/input1/kegg_mnxm_compound_dict.p
antismash/generic_genome_modules/metabolicmodel/input1/kegg_mnxr_dict.p
antismash/generic_genome_modules/metabolicmodel/input1/mnxm_bigg_compound_dict.p
antismash/generic_genome_modules/metabolicmodel/input1/mnxm_compoundInfo_dict.p
antismash/generic_genome_modules/metabolicmodel/input1/mnxm_kegg_compound_dict.p
antismash/generic_genome_modules/metabolicmodel/input1/mnxr_kegg_dict.p
antismash/generic_genome_modules/metabolicmodel/input1/mnxr_rxn_dict.p
antismash/generic_genome_modules/metabolicmodel/input1/eco/model.p
antismash/generic_genome_modules/metabolicmodel/input1/eco/tempBlastDB.phr
antismash/generic_genome_modules/metabolicmodel/input1/eco/tempBlastDB.pin
antismash/generic_genome_modules/metabolicmodel/input1/eco/tempBlastDB.psq
antismash/generic_genome_modules/metabolicmodel/input1/eco/tempModel_biggRxnid_locusTag_dict.p
antismash/generic_genome_modules/metabolicmodel/input1/eco/tempModel_locusTag_aaSeq.fa
antismash/generic_genome_modules/metabolicmodel/input1/sco/model.p
antismash/generic_genome_modules/metabolicmodel/input1/sco/tempBlastDB.phr
plantismash-2.0b4.dist-info/LICENSE.txt
plantismash-2.0b4.dist-info/METADATA
plantismash-2.0b4.dist-info/WHEEL
plantismash-2.0b4.dist-info/entry_points.txt
plantismash-2.0b4.dist-info/top_level.txt
plantismash-2.0b4.dist-info/RECORD
