Metadata-Version: 2.1
Name: plantismash
Version: 2.0b4
Summary: Detection of plant specialized metabolism gene clusters in plants
Author: plantiSMASH authors
License: GNU AFFERO GENERAL PUBLIC LICENSE
Project-URL: Homepage, https://plantismash.bioinformatics.nl/
Project-URL: Source, https://github.com/plantismash/plantismash
Project-URL: Issues, https://github.com/plantismash/plantismash/issues
Keywords: bioinformatics,genomics,secondary metabolism
Classifier: Programming Language :: Python :: 3
Classifier: Programming Language :: Python :: 3 :: Only
Classifier: License :: OSI Approved :: MIT License
Classifier: Operating System :: OS Independent
Classifier: Topic :: Scientific/Engineering :: Bio-Informatics
Requires-Python: <3.9,>=3.8
License-File: LICENSE.txt
Requires-Dist: biopython==1.76
Requires-Dist: numpy==1.24.4
Requires-Dist: cssselect==1.2.0
Requires-Dist: pyquery==1.2.9
Requires-Dist: helperlibs==0.2.2
Requires-Dist: svgwrite==1.4.3
Requires-Dist: openpyxl==3.1.5
Requires-Dist: networkx==3.1
Requires-Dist: python-louvain==0.16
Requires-Dist: bcbio-gff==0.6.7
Requires-Dist: ete3==3.1.3
Requires-Dist: tqdm==4.67.1
Requires-Dist: logomaker
Requires-Dist: MOODS-python==1.9.4.1
Requires-Dist: straight.plugin==1.4.0.post-1
Requires-Dist: appdirs
Provides-Extra: dev
Requires-Dist: pytest; extra == "dev"
